INSTALL.txt
README.txt
setup.py
Products/__init__.py
Products.TemplateFields.egg-info/PKG-INFO
Products.TemplateFields.egg-info/SOURCES.txt
Products.TemplateFields.egg-info/dependency_links.txt
Products.TemplateFields.egg-info/entry_points.txt
Products.TemplateFields.egg-info/namespace_packages.txt
Products.TemplateFields.egg-info/not-zip-safe
Products.TemplateFields.egg-info/requires.txt
Products.TemplateFields.egg-info/top_level.txt
Products/TemplateFields/CHANGES.txt
Products/TemplateFields/LICENSE.txt
Products/TemplateFields/README.txt
Products/TemplateFields/__init__.py
Products/TemplateFields/_field.py
Products/TemplateFields/config.py
Products/TemplateFields/validators.py
Products/TemplateFields/version.txt
Products/TemplateFields/tests/__init__.py
Products/TemplateFields/tests/test_field.py