Metadata-Version: 1.0
Name: Products.TemplateFields
Version: 1.2.5
Summary: Supplies an Archetypes field useful for editing and storing Zope Page Templates
Home-page: http://plone.org/products/scriptablefields
Author: Jens Klein
Author-email: jens@bluedynamics.com
License: GPL
Keywords: Plone ScriptableFields TemplateFields
Platform: UNKNOWN
Classifier: Framework :: Plone
Classifier: Framework :: Zope2
Classifier: Programming Language :: Python
